llama_index/llms/azure_openai/__init__.py
llama_index/llms/azure_openai/base.py
llama_index/llms/azure_openai/utils.py
llama_index_llms_azure_openai-0.4.2.dist-info/METADATA
llama_index_llms_azure_openai-0.4.2.dist-info/WHEEL
llama_index_llms_azure_openai-0.4.2.dist-info/licenses/LICENSE
llama_index_llms_azure_openai-0.4.2.dist-info/RECORD
