Metadata-Version: 2.4
Name: llama-index-llms-azure-openai
Version: 0.4.2
Summary: llama-index llms azure openai integration
Author-email: Your Name <you@example.com>
License-Expression: MIT
License-File: LICENSE
Requires-Python: <4.0,>=3.9
Requires-Dist: azure-identity<2,>=1.15.0
Requires-Dist: httpx
Requires-Dist: llama-index-core<0.15,>=0.14.3
Requires-Dist: llama-index-llms-openai<0.7,>=0.6.0
